pyhost/__init__.py
pyhost/__main__.py
pyhost/dns_type.py
pyhost/resolver.py
pyhost/table.py
pyhost/version.py
pyhost-0.1.0.dist-info/LICENSE
pyhost-0.1.0.dist-info/METADATA
pyhost-0.1.0.dist-info/WHEEL
pyhost-0.1.0.dist-info/top_level.txt
pyhost-0.1.0.dist-info/RECORD
