Metadata-Version: 2.1
Name: pyhost
Version: 0.1.0
Summary: DNS Lookup
Home-page: https://gitlab.com/drewito/pyhost
Author: Javier Poremski
Author-email: javier@poremski.se
License: UNKNOWN
Platform: UNKNOWN
Classifier: Programming Language :: Python :: 3.7
Classifier: License :: OSI Approved :: GNU General Public License v3 (GPLv3)
Classifier: Operating System :: MacOS :: MacOS X
Classifier: Operating System :: POSIX
Classifier: Operating System :: Unix
Requires-Python: >=3.7
